odoo/addons/ssi_odoo_implementation_infrastructure/README.rst
odoo/addons/ssi_odoo_implementation_infrastructure/__init__.py
odoo/addons/ssi_odoo_implementation_infrastructure/__manifest__.py
odoo/addons/ssi_odoo_implementation_infrastructure/models/__init__.py
odoo/addons/ssi_odoo_implementation_infrastructure/models/odoo_implementation.py
odoo/addons/ssi_odoo_implementation_infrastructure/static/description/icon.png
odoo/addons/ssi_odoo_implementation_infrastructure/views/odoo_implementation_views.xml
odoo14_addon_ssi_odoo_implementation_infrastructure-14.0.2.1.0.dist-info/METADATA
odoo14_addon_ssi_odoo_implementation_infrastructure-14.0.2.1.0.dist-info/WHEEL
odoo14_addon_ssi_odoo_implementation_infrastructure-14.0.2.1.0.dist-info/top_level.txt
odoo14_addon_ssi_odoo_implementation_infrastructure-14.0.2.1.0.dist-info/RECORD
